xmsgrid/__init__.py
xmsgrid/_xmsgrid.cp36-win_amd64.pyd
xmsgrid/geometry/__init__.py
xmsgrid/geometry/tri_search.py
xmsgrid/triangulate/__init__.py
xmsgrid/triangulate/tin.py
xmsgrid/ugrid/__init__.py
xmsgrid/ugrid/ugrid.py
xmsgrid/ugrid/ugrid_utils.py
xmsgrid-3.0.1.dist-info/METADATA
xmsgrid-3.0.1.dist-info/WHEEL
xmsgrid-3.0.1.dist-info/dependency_links.txt
xmsgrid-3.0.1.dist-info/top_level.txt
xmsgrid-3.0.1.dist-info/RECORD
